musicbrainz2notion/__about__.py
musicbrainz2notion/__init__.py
musicbrainz2notion/canonical_data_download.py
musicbrainz2notion/canonical_data_processing.py
musicbrainz2notion/config.py
musicbrainz2notion/database_entities.py
musicbrainz2notion/database_utils.py
musicbrainz2notion/environment.py
musicbrainz2notion/main.py
musicbrainz2notion/musicbrainz_data_retrieval.py
musicbrainz2notion/musicbrainz_utils.py
musicbrainz2notion/notion_utils.py
musicbrainz2notion/py.typed
musicbrainz2notion/thumbnails_retrieval.py
musicbrainz2notion-0.5.3.dist-info/METADATA
musicbrainz2notion-0.5.3.dist-info/WHEEL
musicbrainz2notion-0.5.3.dist-info/entry_points.txt
musicbrainz2notion-0.5.3.dist-info/licenses/LICENSE
musicbrainz2notion-0.5.3.dist-info/RECORD
