Metadata-Version: 2.4
Name: musicbrainz2notion
Version: 0.5.3
Summary: A tool to sync artists and music databases from MusicBrainz to Notion.
Project-URL: Repository, https://github.com/Kajiih/musicbrainz2notion
Project-URL: Issues, https://github.com/Kajiih/musicbrainz2notion/issues
Author-email: Kajih <itskajih@gmail.com>
License-File: LICENSE
Keywords: api,database,music,musicbrainz,notion,python,tier list
Classifier: Development Status :: 3 - Alpha
Classifier: Environment :: Console
Classifier: License :: OSI Approved :: MIT License
Classifier: Natural Language :: English
Classifier: Programming Language :: Python
Classifier: Programming Language :: Python :: 3.12
Classifier: Programming Language :: Python :: 3.13
Classifier: Programming Language :: Python :: Implementation :: CPython
Requires-Python: >=3.12
Requires-Dist: bs4>=0.0.2
Requires-Dist: cyclopts>=2.9.9
Requires-Dist: frosch<=0.1.5
Requires-Dist: kajihs-utils[loguru]>=0.2.0
Requires-Dist: loguru>=0.7.2
Requires-Dist: musicbrainzngs>=0.7.1
Requires-Dist: notion-client>=2.2.1
Requires-Dist: pandas>=2.2.3
Requires-Dist: python-dateutil>=2.9.0.post0
Requires-Dist: python-dotenv>=1.0.1
Requires-Dist: rich>=13.9.3
Requires-Dist: tomlkit>=0.13.2
Requires-Dist: toolz>=1.0.0
Requires-Dist: tqdm>=4.66.6
Requires-Dist: typed-settings[attrs,cattrs]>=24.5.0
Requires-Dist: yarl>=1.17
Requires-Dist: zstandard>=0.23.0
